{"annotations": {"0": {"category": "person", "bbox": [214.55, 0.0, 25.89, 36.24]}, "1": {"category": "person", "bbox": [562.39, 62.92, 77.31, 145.23]}, "2": {"category": "person", "bbox": [260.81, 3.3, 24.59, 40.18]}, "3": {"category": "person", "bbox": [340.4, 2.45, 39.15, 102.78]}, "4": {"category": "person", "bbox": [536.88, 44.15, 43.19, 46.02]}, "5": {"category": "person", "bbox": [390.9, 21.5, 38.88, 141.81]}, "6": {"category": "person", "bbox": [571.61, 127.47, 68.39, 137.86]}, "7": {"category": "person", "bbox": [140.53, 0.0, 69.52, 212.81]}, "8": {"category": "person", "bbox": [351.19, 73.61, 30.82, 41.28]}, "9": {"category": "person", "bbox": [409.86, 17.6, 28.15, 99.29]}, "10": {"category": "person", "bbox": [237.37, 0.0, 17.03, 23.67]}, "11": {"category": "person", "bbox": [586.28, 97.37, 53.55, 137.11]}, "12": {"category": "person", "bbox": [364.05, 10.6, 55.96, 106.38]}, "13": {"category": "person", "bbox": [267.35, 0.0, 81.79, 90.74]}, "14": {"category": "person", "bbox": [0.0, 0.0, 90.17, 276.97]}, "15": {"category": "person", "bbox": [82.3, 0.42, 72.86, 149.14]}, "16": {"category": "motorcycle", "bbox": [112.96, 14.42, 395.36, 402.17]}, "17": {"category": "motorcycle", "bbox": [490.96, 59.87, 89.59, 125.89]}, "18": {"category": "motorcycle", "bbox": [58.02, 30.7, 141.69, 127.58]}}, "width": 640, "height": 425, "source": "LVIS"}