{"annotations": {"0": {"category": "bracelet", "bbox": [585.7, 470.27, 28.34, 9.73]}, "1": {"category": "bracelet", "bbox": [210.14, 328.99, 31.47, 23.67]}, "2": {"category": "plastic_bag", "bbox": [85.78, 287.75, 32.47, 41.9]}, "3": {"category": "refrigerator", "bbox": [20.27, 23.95, 92.95, 179.2]}, "4": {"category": "person", "bbox": [32.83, 94.06, 84.1, 231.28]}, "5": {"category": "person", "bbox": [141.77, 0.0, 498.23, 480.0]}, "6": {"category": "sunglasses", "bbox": [273.4, 37.22, 138.78, 59.69]}, "7": {"category": "sweatshirt", "bbox": [224.01, 138.16, 415.99, 341.84]}}, "width": 640, "height": 480, "source": "LVIS"}