{"annotations": {"0": {"category": "Human face", "bbox": [252, 75, 225, 273]}, "1": {"category": "Human hair", "bbox": [257, 76, 220, 204]}, "2": {"category": "Person", "bbox": [214, 78, 424, 725]}, "3": {"category": "Human body", "bbox": [214, 68, 424, 734]}, "4": {"category": "Human head", "bbox": [253, 73, 225, 271]}, "5": {"category": "Human eye", "bbox": [341, 305, 23, 9]}, "6": {"category": "Boy", "bbox": [324, 273, 202, 329]}, "7": {"category": "Human leg", "bbox": [198, 476, 161, 225]}, "8": {"category": "Human leg", "bbox": [443, 511, 199, 297]}, "9": {"category": "Car", "bbox": [122, 378, 207, 239]}, "10": {"category": "Human nose", "bbox": [325, 301, 25, 27]}, "11": {"category": "Clothing", "bbox": [322, 266, 204, 335]}, "12": {"category": "Human hand", "bbox": [234, 351, 73, 47]}, "13": {"category": "Human hand", "bbox": [247, 512, 67, 68]}, "14": {"category": "Footwear", "bbox": [586, 164, 121, 52]}, "15": {"category": "Footwear", "bbox": [689, 170, 65, 49]}, "16": {"category": "Wheel", "bbox": [172, 584, 27, 25]}, "17": {"category": "Wheel", "bbox": [217, 504, 49, 57]}, "18": {"category": "Toy", "bbox": [0, 579, 44, 183]}, "19": {"category": "Toy", "bbox": [0, 795, 31, 167]}, "20": {"category": "Toy", "bbox": [0, 800, 31, 54]}, "21": {"category": "Toy", "bbox": [0, 857, 35, 97]}, "22": {"category": "Toy", "bbox": [30, 817, 150, 91]}, "23": {"category": "Toy", "bbox": [122, 380, 209, 239]}, "24": {"category": "Toy", "bbox": [328, 589, 71, 55]}, "25": {"category": "Human arm", "bbox": [234, 322, 103, 76]}, "26": {"category": "Human arm", "bbox": [244, 404, 249, 172]}}, "width": 765, "height": 1024, "source": "OpenImages"}