{"source": "LVIS", "workerId": "annotator408", "defaultAnnotation": {"signboard": {"category": "signboard", "informationType": "", "informationTypeInput": "", "informativeness": 0, "sharingOwner": [], "sharingOwnerInput": "", "sharingOthers": [], "sharingOthersInput": "", "ifNoPrivacy": true}, "license_plate": {"category": "license_plate", "informationType": [1, 0, 0, 0, 0, 0], "informationTypeInput": "", "informativeness": "4", "sharingOwner": [1, 0, 0, 0, 0, 0, 0], "sharingOwnerInput": "", "sharingOthers": [1, 0, 0, 0, 0, 0, 0], "sharingOthersInput": "", "ifNoPrivacy": false}, "street_sign": {"category": "street_sign", "informationType": "", "informationTypeInput": "", "informativeness": 0, "sharingOwner": [], "sharingOwnerInput": "", "sharingOthers": [], "sharingOthersInput": "", "ifNoPrivacy": true}, "shoulder_bag": {"category": "shoulder_bag", "informationType": "", "informationTypeInput": "", "informativeness": 0, "sharingOwner": [], "sharingOwnerInput": "", "sharingOthers": [], "sharingOthersInput": "", "ifNoPrivacy": true}}, "manualAnnotation": {}}