{"source": "OpenImages", "workerId": "annotator446", "defaultAnnotation": {"Human hair": {"category": "Human hair", "informationType": "", "informationTypeInput": "", "informativeness": 0, "sharingOwner": [], "sharingOwnerInput": "", "sharingOthers": [], "sharingOthersInput": "", "ifNoPrivacy": true}, "Clothing": {"category": "Clothing", "informationType": [0, 0, 1, 0, 0, 0], "informationTypeInput": "", "informativeness": "5", "sharingOwner": [0, 1, 0, 0, 0, 0, 0], "sharingOwnerInput": "", "sharingOthers": [0, 0, 1, 0, 0, 0, 0], "sharingOthersInput": "", "ifNoPrivacy": false}, "Human body": {"category": "Human body", "informationType": "", "informationTypeInput": "", "informativeness": 0, "sharingOwner": [], "sharingOwnerInput": "", "sharingOthers": [], "sharingOthersInput": "", "ifNoPrivacy": true}, "Mammal": {"category": "Mammal", "informationType": [1, 0, 1, 0, 0, 0], "informationTypeInput": "", "informativeness": "6", "sharingOwner": [0, 1, 0, 0, 0, 0, 0], "sharingOwnerInput": "", "sharingOthers": [0, 1, 0, 0, 0, 0, 0], "sharingOthersInput": "", "ifNoPrivacy": false}, "Human arm": {"category": "Human arm", "informationType": "", "informationTypeInput": "", "informativeness": 0, "sharingOwner": [], "sharingOwnerInput": "", "sharingOthers": [], "sharingOthersInput": "", "ifNoPrivacy": true}, "Man": {"category": "Man", "informationType": [1, 0, 1, 0, 0, 0], "informationTypeInput": "", "informativeness": "5", "sharingOwner": [0, 1, 0, 0, 0, 0, 0], "sharingOwnerInput": "", "sharingOthers": [0, 1, 0, 0, 0, 0, 0], "sharingOthersInput": "", "ifNoPrivacy": false}}, "manualAnnotation": {}}