{"source": "OpenImages", "workerId": "annotator426", "defaultAnnotation": {"Human face": {"category": "Human face", "informationType": [1, 0, 0, 0, 0, 0], "informationTypeInput": "", "informativeness": "7", "sharingOwner": [1, 0, 0, 0, 0, 0, 0], "sharingOwnerInput": "", "sharingOthers": [1, 0, 0, 0, 0, 0, 0], "sharingOthersInput": "", "ifNoPrivacy": false}, "Human hair": {"category": "Human hair", "informationType": "", "informationTypeInput": "", "informativeness": 0, "sharingOwner": [], "sharingOwnerInput": "", "sharingOthers": [], "sharingOthersInput": "", "ifNoPrivacy": true}}, "manualAnnotation": {}}