{"annotations": {"0": {"category": "Human leg", "bbox": [56, 359, 97, 461]}, "1": {"category": "Human leg", "bbox": [86, 381, 158, 438]}, "2": {"category": "Human leg", "bbox": [328, 755, 141, 40]}, "3": {"category": "Human leg", "bbox": [558, 746, 197, 64]}, "4": {"category": "Human leg", "bbox": [638, 748, 223, 71]}, "5": {"category": "Human leg", "bbox": [642, 743, 255, 80]}, "6": {"category": "Girl", "bbox": [42, 30, 425, 784]}, "7": {"category": "Girl", "bbox": [557, 470, 419, 346]}, "8": {"category": "Person", "bbox": [151, 671, 783, 124]}, "9": {"category": "Clothing", "bbox": [30, 126, 993, 686]}, "10": {"category": "Human body", "bbox": [42, 30, 981, 785]}, "11": {"category": "Brassiere", "bbox": [766, 576, 139, 105]}, "12": {"category": "Swimwear", "bbox": [71, 126, 149, 332]}, "13": {"category": "Swimwear", "bbox": [751, 579, 151, 194]}, "14": {"category": "Woman", "bbox": [42, 22, 422, 792]}, "15": {"category": "Woman", "bbox": [555, 470, 425, 351]}}, "width": 1024, "height": 871, "source": "OpenImages"}