{"annotations": {"0": {"category": "Person", "bbox": [140, 102, 16, 66]}, "1": {"category": "Person", "bbox": [191, 107, 54, 151]}, "2": {"category": "Person", "bbox": [291, 355, 46, 151]}, "3": {"category": "Person", "bbox": [293, 388, 43, 145]}, "4": {"category": "Person", "bbox": [385, 349, 36, 161]}, "5": {"category": "Person", "bbox": [430, 336, 54, 199]}, "6": {"category": "Man", "bbox": [155, 67, 49, 193]}, "7": {"category": "Man", "bbox": [249, 60, 46, 86]}, "8": {"category": "Man", "bbox": [353, 318, 58, 234]}, "9": {"category": "Man", "bbox": [433, 333, 63, 213]}}, "width": 1024, "height": 683, "source": "OpenImages"}