{"annotations": {"0": {"category": "passport", "bbox": [33.72, 285.11, 63.49, 33.22]}, "1": {"category": "monitor_(computer_equipment) computer_monitor", "bbox": [210.15, 106.36, 205.89, 114.47]}, "2": {"category": "monitor_(computer_equipment) computer_monitor", "bbox": [457.0, 18.12, 168.79, 233.12]}, "3": {"category": "monitor_(computer_equipment) computer_monitor", "bbox": [534.28, 222.57, 102.97, 78.38]}, "4": {"category": "monitor_(computer_equipment) computer_monitor", "bbox": [1.48, 171.76, 162.23, 119.12]}, "5": {"category": "microphone", "bbox": [122.11, 102.26, 72.0, 111.98]}, "6": {"category": "speaker_(stero_equipment)", "bbox": [169.05, 121.72, 42.82, 135.35]}, "7": {"category": "speaker_(stero_equipment)", "bbox": [414.84, 132.78, 48.15, 119.01]}, "8": {"category": "computer_keyboard", "bbox": [213.14, 272.08, 217.95, 55.07]}, "9": {"category": "mouse_(computer_equipment)", "bbox": [463.97, 276.81, 33.62, 35.96]}}, "width": 640, "height": 410, "source": "LVIS"}