{"annotations": {"0": {"category": "Skyscraper", "bbox": [440, 290, 43, 93]}, "1": {"category": "Skyscraper", "bbox": [521, 328, 31, 69]}, "2": {"category": "Skyscraper", "bbox": [552, 328, 28, 75]}, "3": {"category": "Skyscraper", "bbox": [582, 344, 34, 58]}, "4": {"category": "Traffic sign", "bbox": [467, 489, 21, 24]}, "5": {"category": "Traffic sign", "bbox": [839, 494, 15, 27]}, "6": {"category": "Traffic sign", "bbox": [884, 461, 33, 54]}, "7": {"category": "Traffic sign", "bbox": [925, 512, 30, 25]}, "8": {"category": "Building", "bbox": [311, 290, 308, 114]}, "9": {"category": "Building", "bbox": [654, 371, 65, 36]}, "10": {"category": "Building", "bbox": [732, 332, 290, 72]}}, "width": 1024, "height": 685, "source": "OpenImages"}