{"source": "LVIS", "workerId": "annotator104", "defaultAnnotation": {"orange_juice": {"category": "orange_juice", "informationType": "", "informationTypeInput": "", "informativeness": 0, "sharingOwner": [], "sharingOwnerInput": "", "sharingOthers": [], "sharingOthersInput": "", "ifNoPrivacy": true}, "chair": {"category": "chair", "informationType": "", "informationTypeInput": "", "informativeness": 0, "sharingOwner": [], "sharingOwnerInput": "", "sharingOthers": [], "sharingOthersInput": "", "ifNoPrivacy": true}, "table": {"category": "table", "informationType": "", "informationTypeInput": "", "informativeness": 0, "sharingOwner": [], "sharingOwnerInput": "", "sharingOthers": [], "sharingOthersInput": "", "ifNoPrivacy": true}, "place_mat": {"category": "place_mat", "informationType": "", "informationTypeInput": "", "informativeness": 0, "sharingOwner": [], "sharingOwnerInput": "", "sharingOthers": [], "sharingOthersInput": "", "ifNoPrivacy": true}, "laptop_computer": {"category": "laptop_computer", "informationType": [0, 0, 0, 1, 0, 0], "informationTypeInput": "", "informativeness": "1", "sharingOwner": [0, 1, 0, 0, 0, 0, 0], "sharingOwnerInput": "", "sharingOthers": [0, 1, 0, 0, 0, 0, 0], "sharingOthersInput": "", "ifNoPrivacy": false}, "spoon": {"category": "spoon", "informationType": "", "informationTypeInput": "", "informativeness": 0, "sharingOwner": [], "sharingOwnerInput": "", "sharingOthers": [], "sharingOthersInput": "", "ifNoPrivacy": true}, "watermelon": {"category": "watermelon", "informationType": "", "informationTypeInput": "", "informativeness": 0, "sharingOwner": [], "sharingOwnerInput": "", "sharingOthers": [], "sharingOthersInput": "", "ifNoPrivacy": true}}, "manualAnnotation": {}}