{"source": "LVIS", "workerId": "annotator90", "defaultAnnotation": {"drum_(musical_instrument)": {"category": "drum_(musical_instrument)", "informationType": "", "informationTypeInput": "", "informativeness": 0, "sharingOwner": [], "sharingOwnerInput": "", "sharingOthers": [], "sharingOthersInput": "", "ifNoPrivacy": true}, "television_set": {"category": "television_set", "informationType": [0, 0, 0, 1, 0, 0], "informationTypeInput": "", "informativeness": "2", "sharingOwner": [0, 1, 1, 0, 0, 0, 0], "sharingOwnerInput": "", "sharingOthers": [0, 1, 0, 0, 0, 0, 0], "sharingOthersInput": "", "ifNoPrivacy": false}}, "manualAnnotation": {"0": {"category": "\u7537\u6027", "bbox": [143.96350745792753, 66.97740637174873, 485.55950512751116, 290.8940330882969], "informationType": [1, 1, 0, 1, 0, 0], "informationTypeInput": "", "informativeness": "7", "sharingOwner": [1, 0, 0, 0, 0, 0, 0], "sharingOwnerInput": "", "sharingOthers": [1, 0, 0, 0, 0, 0, 0], "sharingOthersInput": ""}}}