{"source": "OpenImages", "workerId": "annotator333", "defaultAnnotation": {"Bus": {"category": "Bus", "informationType": "", "informationTypeInput": "", "informativeness": 0, "sharingOwner": [], "sharingOwnerInput": "", "sharingOthers": [], "sharingOthersInput": "", "ifNoPrivacy": true}, "Van": {"category": "Van", "informationType": "", "informationTypeInput": "", "informativeness": 0, "sharingOwner": [], "sharingOwnerInput": "", "sharingOthers": [], "sharingOthersInput": "", "ifNoPrivacy": true}, "Vehicle registration plate": {"category": "Vehicle registration plate", "informationType": [0, 0, 0, 0, 0, 1], "informationTypeInput": "Reg number of vehicle", "informativeness": "3", "sharingOwner": [1, 0, 0, 0, 0, 0, 0], "sharingOwnerInput": "", "sharingOthers": [1, 0, 0, 0, 0, 0, 0], "sharingOthersInput": "", "ifNoPrivacy": false}, "Clothing": {"category": "Clothing", "informationType": "", "informationTypeInput": "", "informativeness": 0, "sharingOwner": [], "sharingOwnerInput": "", "sharingOthers": [], "sharingOthersInput": "", "ifNoPrivacy": true}, "Auto part": {"category": "Auto part", "informationType": "", "informationTypeInput": "", "informativeness": 0, "sharingOwner": [], "sharingOwnerInput": "", "sharingOthers": [], "sharingOthersInput": "", "ifNoPrivacy": true}}, "manualAnnotation": {}}