{"source": "OpenImages", "workerId": "annotator322", "defaultAnnotation": {"Human face": {"category": "Human face", "informationType": [1, 0, 0, 0, 0, 0], "informationTypeInput": "", "informativeness": "7", "sharingOwner": [0, 1, 1, 0, 0, 0, 0], "sharingOwnerInput": "", "sharingOthers": [1, 0, 0, 0, 0, 0, 0], "sharingOthersInput": "", "ifNoPrivacy": false}, "Human hair": {"category": "Human hair", "informationType": "", "informationTypeInput": "", "informativeness": 0, "sharingOwner": [], "sharingOwnerInput": "", "sharingOthers": [], "sharingOthersInput": "", "ifNoPrivacy": true}, "Girl": {"category": "Girl", "informationType": [0, 0, 1, 0, 0, 0], "informationTypeInput": "", "informativeness": "6", "sharingOwner": [0, 1, 1, 1, 0, 0, 0], "sharingOwnerInput": "", "sharingOthers": [1, 0, 0, 0, 0, 0, 0], "sharingOthersInput": "", "ifNoPrivacy": false}, "Crown": {"category": "Crown", "informationType": [0, 0, 1, 0, 0, 0], "informationTypeInput": "", "informativeness": "2", "sharingOwner": [0, 1, 1, 1, 1, 1, 0], "sharingOwnerInput": "", "sharingOthers": [0, 0, 0, 1, 0, 0, 0], "sharingOthersInput": "", "ifNoPrivacy": false}, "Human nose": {"category": "Human nose", "informationType": "", "informationTypeInput": "", "informativeness": 0, "sharingOwner": [], "sharingOwnerInput": "", "sharingOthers": [], "sharingOthersInput": "", "ifNoPrivacy": true}, "Clothing": {"category": "Clothing", "informationType": [0, 1, 1, 1, 0, 0], "informationTypeInput": "", "informativeness": "5", "sharingOwner": [0, 0, 0, 1, 0, 0, 0], "sharingOwnerInput": "", "sharingOthers": [0, 1, 0, 0, 0, 0, 0], "sharingOthersInput": "", "ifNoPrivacy": false}, "Human body": {"category": "Human body", "informationType": [1, 0, 1, 1, 1, 0], "informationTypeInput": "", "informativeness": "6", "sharingOwner": [0, 1, 0, 0, 0, 0, 0], "sharingOwnerInput": "", "sharingOthers": [1, 0, 0, 0, 0, 0, 0], "sharingOthersInput": "", "ifNoPrivacy": false}, "Human eye": {"category": "Human eye", "informationType": [1, 0, 0, 0, 0, 0], "informationTypeInput": "", "informativeness": "7", "sharingOwner": [0, 1, 0, 0, 0, 0, 0], "sharingOwnerInput": "", "sharingOthers": [1, 0, 0, 0, 0, 0, 0], "sharingOthersInput": "", "ifNoPrivacy": false}, "Human ear": {"category": "Human ear", "informationType": "", "informationTypeInput": "", "informativeness": 0, "sharingOwner": [], "sharingOwnerInput": "", "sharingOthers": [], "sharingOthersInput": "", "ifNoPrivacy": true}, "Human mouth": {"category": "Human mouth", "informationType": [1, 0, 0, 0, 0, 0], "informationTypeInput": "", "informativeness": "4", "sharingOwner": [0, 1, 0, 0, 0, 0, 0], "sharingOwnerInput": "", "sharingOthers": [0, 1, 0, 0, 0, 0, 0], "sharingOthersInput": "", "ifNoPrivacy": false}, "Woman": {"category": "Woman", "informationType": [1, 0, 1, 1, 0, 0], "informationTypeInput": "", "informativeness": "6", "sharingOwner": [0, 1, 0, 0, 0, 0, 0], "sharingOwnerInput": "", "sharingOthers": [0, 1, 0, 0, 0, 0, 0], "sharingOthersInput": "", "ifNoPrivacy": false}}, "manualAnnotation": {}}